{
  "users": [
    {
      "id": 1,
      "username": "tj",
      "password": "03ac674216f3e15c761ee1a5e255f067953623c8b388b4459e13f978d7c846f4",
      "avatar": "https://api.dicebear.com/7.x/adventurer/svg?seed=tj&backgroundColor=b6e3f4",
      "nickname": "tj同学",
      "current_task": "大数据导论",
      "created_at": "local",
      "last_login": "local"
    }
  ],
  "learning_records": [],
  "user_profiles": [
    {
      "id": 1,
      "user_id": 1,
      "profile_json": "{\"knowledgeBase\": \"零基础入门\", \"codeSkill\": \"编程新手\", \"learningGoal\": \"职业发展\", \"cognitiveStyle\": \"实践型\", \"weakness\": \"暂无\", \"focusLevel\": \"中等专注\", \"learningDirection\": \"前端开发\", \"languages\": [\"scala\", \"rust\", \"python\", \"javascript\", \"java\", \"c\", \"go\", \"cpp\", \"sql\"]}",
      "evaluation_json": "{}",
      "last_grade_record": null,
      "updated_at": "local"
    }
  ],
  "learning_paths": [
    {
      "id": 1,
      "user_id": 1,
      "path_json": "[{\"topic\": \"HTML/CSS基础\", \"status\": \"current\", \"desc\": \"网页结构、样式设计\"}, {\"topic\": \"JavaScript入门\", \"status\": \"locked\", \"desc\": \"JS语法、DOM操作\"}, {\"topic\": \"ES6+与TypeScript\", \"status\": \"locked\", \"desc\": \"现代JS、类型系统\"}, {\"topic\": \"React/Vue框架\", \"status\": \"locked\", \"desc\": \"组件化开发\"}, {\"topic\": \"前端工程化\", \"status\": \"locked\", \"desc\": \"Webpack、Vite、CI/CD\"}, {\"topic\": \"项目实战\", \"status\": \"locked\", \"desc\": \"完整前端项目\"}]",
      "updated_at": "local"
    }
  ]
}